xia_module_gcp_bigquery/__init__.py
xia_module_gcp_bigquery/dataset.py
xia_module_gcp_bigquery/table.py
xia_module_gcp_bigquery/templates/gcp-module-dataset/activate/main.tf
xia_module_gcp_bigquery/templates/gcp-module-dataset/activate/variables.tf
xia_module_gcp_bigquery/templates/gcp-module-dataset/base/activate.tf
xia_module_gcp_bigquery/templates/gcp-module-dataset/base/main.tf
xia_module_gcp_bigquery/templates/gcp-module-dataset/cicd/github/workflow.yml
xia_module_gcp_bigquery/templates/gcp-module-dataset/config/gcp/datasets/dataset_example.yaml
xia_module_gcp_bigquery/templates/gcp-module-dataset/config/platform/gcp-project.yaml
xia_module_gcp_bigquery/templates/gcp-module-dataset/module/main.tf
xia_module_gcp_bigquery/templates/gcp-module-dataset/module/variables.tf
xia_module_gcp_bigquery/templates/gcp-module-table/activate/main.tf
xia_module_gcp_bigquery/templates/gcp-module-table/activate/variables.tf
xia_module_gcp_bigquery/templates/gcp-module-table/base/activate.tf
xia_module_gcp_bigquery/templates/gcp-module-table/base/main.tf
xia_module_gcp_bigquery/templates/gcp-module-table/module/main.tf
xia_module_gcp_bigquery/templates/gcp-module-table/module/variables.tf
xia_module_gcp_bigquery-0.0.26.dist-info/LICENSE
xia_module_gcp_bigquery-0.0.26.dist-info/METADATA
xia_module_gcp_bigquery-0.0.26.dist-info/WHEEL
xia_module_gcp_bigquery-0.0.26.dist-info/top_level.txt
xia_module_gcp_bigquery-0.0.26.dist-info/RECORD
