Metadata-Version: 2.1
Name: xia-module-gcp-bigquery
Version: 0.0.26
Requires-Python: >=3.9
License-File: LICENSE
Requires-Dist: xia-module
